Metadata-Version: 2.1
Name: basic-web-server
Version: 0.4
Summary: A basic web server that can render HTML or plain text.
Home-page: https://github.com/kaimv/basic-webserver
Author: kaimv
Author-email: kaimv.hi@gmail.com
Requires-Dist: http
